LICENSE
setup.py
hamlpy/__init__.py
hamlpy/elements.py
hamlpy/ext.py
hamlpy/hamlpy.py
hamlpy/hamlpy_watcher.py
hamlpy/nodes.py
hamlpy/templatize.py
hamlpy/template/__init__.py
hamlpy/template/loaders.py
hamlpy/template/utils.py
spc_hamlpy.egg-info/PKG-INFO
spc_hamlpy.egg-info/SOURCES.txt
spc_hamlpy.egg-info/dependency_links.txt
spc_hamlpy.egg-info/entry_points.txt
spc_hamlpy.egg-info/top_level.txt