Metadata-Version: 2.1
Name: spc-hamlpy
Version: 1.0.0
Summary: HAML like syntax for Django templates
Home-page: http://github.com/jessemiller/HamlPy
Download-URL: http://github.com/jessemiller/HamlPy
Author: blacktear23
Author-email: blacktear23@gmail.com
License: MIT
Keywords: haml django converter
Classifier: Development Status :: 4 - Beta
Classifier: Operating System :: OS Independent
Classifier: License :: OSI Approved :: BSD License
Classifier: Programming Language :: Python :: 3
Classifier: Programming Language :: Python :: Implementation :: CPython
Classifier: Topic :: Software Development :: Libraries
License-File: LICENSE
